{"type": "root", "attrs": {"type": "example"}, "body": [{"type": "title", "indent": 0, "text": ["Slope"]}, {"type": "para", "indent": 0, "text": ["This example demonstrates how the Slope CHOP calculates the slope (or derivative) of the input channels."], "extent": [0, 106]}, {"type": "para", "indent": 0, "text": ["If the input CHOP represents position, the slope can be interpreted as speed."], "extent": [106, 185]}, {"type": "para", "indent": 0, "text": ["By default, the Slope CHOP converts position to speed."], "extent": [185, 240]}], "examplefor": "/nodes/chop/slope", "examplefile": "/examples/nodes/chop/slope/Slope.otl"}