{"type": "root", "attrs": {"type": "example"}, "body": [{"type": "title", "indent": 0, "text": ["ChoreographedBreakup"]}, {"type": "para", "indent": 0, "text": ["This example shows how one can control the break up of any glued\nobject through the use of the RBD State node."], "extent": [0, 112]}, {"type": "para", "indent": 0, "text": ["A torus, composed of spheres, is glued together.  An additional\nsweep plane is defined.  Any sphere which ends up on the wrong side of\nthe sweep plane is broken off the torus and left to bounce on its own.\nThis lets the break up of the torus to be controlled over many\nframes."], "extent": [112, 389]}], "examplefor": "/nodes/dop/rbdglueobject", "examplefile": "/examples/nodes/dop/rbdglueobject/ChoreographedBreakup.otl"}