{"type": "root", "attrs": {"icon": "FUR/paint_frizz", "parent": "guideprocess"}, "body": [{"level": 0, "type": "title", "indent": 0, "text": ["Frizz Guides"], "extent": [46, 63]}, {"type": "summary", "indent": 0, "text": ["Offsets the curve points along the guide hairs to create a frizzy look."], "extent": [63, 143]}, {"level": 2, "id": null, "container": true, "type": "h", "indent": 0, "text": ["Overview"], "extent": [143, 158], "body": [{"type": "para", "indent": 0, "text": ["This tool offsets curve points along the guide hairs using noise, varying along the curve\u2019s length and different for each curve."], "extent": [158, 289]}, {"type": "para", "indent": 0, "text": ["Clicking ", {"scheme": "Icon", "value": "FUR/paint_frizz", "type": "link", "text": "", "fullpath": "/shelf/FUR/paint_frizz"}, " ", {"type": "ui", "text": ["Frizz Guides"]}, " on the ", {"type": "ui", "text": ["Guide Process"]}, " tab will put down a ", {"scheme": "Node", "value": "/nodes/sop/guideprocess", "type": "link", "text": ["Guide Process SOP"], "fullpath": "/nodes/sop/guideprocess"}, " with the ", {"type": "ui", "text": ["Operation"]}, " parameter set to ", {"type": "ui", "text": ["Frizz"]}, ".  For more information, see the ", {"scheme": "Node", "value": "/nodes/sop/guideprocess", "type": "link", "text": ["Guide Process SOP"], "fullpath": "/nodes/sop/guideprocess"}, " help page."], "extent": [289, 561]}]}], "title": ["Frizz Guides"], "summary": ["Offsets the curve points along the guide hairs to create a frizzy look."]}