{"type": "root", "attrs": {"icon": "FUR/paint_straighten", "parent": "guideprocess"}, "body": [{"level": 0, "type": "title", "indent": 0, "text": ["Straighten Guides"], "extent": [51, 73]}, {"type": "summary", "indent": 0, "text": ["Straightens the hair by bending each segment back so that it\u2019s in the same direction as the previous segment."], "extent": [73, 191]}, {"level": 2, "id": null, "container": true, "type": "h", "indent": 0, "text": ["Overview"], "extent": [191, 206], "body": [{"type": "para", "indent": 0, "text": ["This tool straightens the hair by bending each segment back so that it\u2019s in the same direction as the previous segment. This effectively removes any bending, frizz, etc. that was previously applied."], "extent": [206, 407]}, {"type": "para", "indent": 0, "text": ["Clicking ", {"scheme": "Icon", "value": "FUR/paint_straighten", "type": "link", "text": "", "fullpath": "/shelf/FUR/paint_straighten"}, " ", {"type": "ui", "text": ["Straighten Guides"]}, " on the ", {"type": "ui", "text": ["Guide Process"]}, " tab will put down a ", {"scheme": "Node", "value": "/nodes/sop/guideprocess", "type": "link", "text": ["Guide Process SOP"], "fullpath": "/nodes/sop/guideprocess"}, " with the ", {"type": "ui", "text": ["Operation"]}, " parameter set to ", {"type": "ui", "text": ["Straighten"]}, ". For more information, see the ", {"scheme": "Node", "value": "/nodes/sop/guideprocess", "type": "link", "text": ["Guide Process SOP"], "fullpath": "/nodes/sop/guideprocess"}, " help page."], "extent": [407, 692]}]}], "title": ["Straighten Guides"], "summary": ["Straightens the hair by bending each segment back so that it\u2019s in the same direction as the previous segment."]}